Metadata-Version: 2.4
Name: livekit-plugins-google-extended
Version: 0.1.1
Summary: Agent Framework plugin for services from Google Cloud
Project-URL: Documentation, https://github.com/Harsh-Mahajan-Copart/livekit-plugins-google-extended/blob/main/README.md
Project-URL: Source, https://github.com/Harsh-Mahajan-Copart/livekit-plugins-google-extended
Author: Harsh Mahajan
License-Expression: Apache-2.0
License-File: LICENSE
License-File: NOTICE
Keywords: ai,anthropic,audio,claude,gemini,google,livekit,realtime,video,voice
Classifier: Intended Audience :: Developers
Classifier: License :: OSI Approved :: Apache Software License
Classifier: Programming Language :: Python :: 3
Classifier: Programming Language :: Python :: 3 :: Only
Classifier: Programming Language :: Python :: 3.9
Classifier: Programming Language :: Python :: 3.10
Classifier: Topic :: Multimedia :: Sound/Audio
Classifier: Topic :: Multimedia :: Video
Classifier: Topic :: Scientific/Engineering :: Artificial Intelligence
Requires-Python: >=3.10
Requires-Dist: google-auth<3,>=2
Requires-Dist: google-cloud-speech<3,>=2
Requires-Dist: google-cloud-texttospeech<3,>=2.32
Requires-Dist: google-genai>=1.55; python_version >= '3.10'
Requires-Dist: livekit-agents>=1.3.6
